shmtu_auth/__init__.py
shmtu_auth/__main__.py
shmtu_auth/main_gui.py
shmtu_auth/main_pyinstaller.py
shmtu_auth/main_start.py
shmtu_auth/version.py
shmtu_auth/config/__init__.py
shmtu_auth/config/end_line.py
shmtu_auth/config/generate_env_script.py
shmtu_auth/config/github/__init__.py
shmtu_auth/config/github/latest_version.py
shmtu_auth/scripts/__init__.py
shmtu_auth/src/__init__.py
shmtu_auth/src/entry.py
shmtu_auth/src/parse_args.py
shmtu_auth/src/config/__init__.py
shmtu_auth/src/config/build_info.py
shmtu_auth/src/config/config_global.py
shmtu_auth/src/config/config_toml.py
shmtu_auth/src/config/data_directory.py
shmtu_auth/src/config/project_directory.py
shmtu_auth/src/core/__init__.py
shmtu_auth/src/core/core.py
shmtu_auth/src/core/core_exp.py
shmtu_auth/src/core/get_query_string_requests.py
shmtu_auth/src/core/ismu.py
shmtu_auth/src/core/query_string.py
shmtu_auth/src/core/shmtu_auth.py
shmtu_auth/src/core/shmtu_auth_const_value.py
shmtu_auth/src/datatype/__init__.py
shmtu_auth/src/datatype/shmtu/__init__.py
shmtu_auth/src/datatype/shmtu/auth/__init__.py
shmtu_auth/src/datatype/shmtu/auth/auth_user.py
shmtu_auth/src/gui/__init__.py
shmtu_auth/src/gui/gui_main_application.py
shmtu_auth/src/gui/common/__init__.py
shmtu_auth/src/gui/common/config.py
shmtu_auth/src/gui/common/font_confg.py
shmtu_auth/src/gui/common/signal_bus.py
shmtu_auth/src/gui/common/style_sheet.py
shmtu_auth/src/gui/common/system_menu.py
shmtu_auth/src/gui/common/components/__init__.py
shmtu_auth/src/gui/common/components/link_card.py
shmtu_auth/src/gui/common/components/sample_card.py
shmtu_auth/src/gui/feature/__init__.py
shmtu_auth/src/gui/feature/network_auth.py
shmtu_auth/src/gui/resource/__init__.py
shmtu_auth/src/gui/resource/resources.py
shmtu_auth/src/gui/software/__init__.py
shmtu_auth/src/gui/software/program_update.py
shmtu_auth/src/gui/task/__init__.py
shmtu_auth/src/gui/task/check_update.py
shmtu_auth/src/gui/task/task_center.py
shmtu_auth/src/gui/utils/async_network_test.py
shmtu_auth-2.2.0.dist-info/licenses/LICENSE
shmtu_auth-2.2.0.dist-info/METADATA
shmtu_auth-2.2.0.dist-info/WHEEL
shmtu_auth-2.2.0.dist-info/entry_points.txt
shmtu_auth-2.2.0.dist-info/top_level.txt
shmtu_auth-2.2.0.dist-info/RECORD
