Metadata-Version: 2.4
Name: shmtu-auth
Version: 2.2.0
Summary: 上海海事大学校园网自动认证工具
Author-email: Haomin Kong <a645162@gmail.com>
License: GPLv3
Project-URL: Homepage, https://github.com/a645162/shmtu-auth
Requires-Python: >=3.8
License-File: LICENSE
Requires-Dist: urllib3<2
Requires-Dist: requests>=2.20.0
Requires-Dist: chardet>=3.0.0
Requires-Dist: PyYaml>=5.1.0
Requires-Dist: toml>=0.10.0
Requires-Dist: loguru>=0.5.0
Dynamic: license-file
